README.rst
setup.cfg
setup.py
bin/os-package-versions
versions_client/__init__.py
versions_client/utils.py
versions_client.egg-info/PKG-INFO
versions_client.egg-info/SOURCES.txt
versions_client.egg-info/dependency_links.txt
versions_client.egg-info/not-zip-safe
versions_client.egg-info/requires.txt
versions_client.egg-info/top_level.txt
versions_client/django/__init__.py
versions_client/django/auth.py
versions_client/django/urls.py
versions_client/django/views.py