Metadata-Version: 1.2
Name: versions-client
Version: 0.2
Summary: Fetch software versions from your app for Prometheus.
Home-page: https://gitlab.com/mediamoose/versions-client/tree/v0.2
Author: Maikel Vlasman (Mediamoose)
Author-email: maikel@mediamoose.nl
License: MIT
Download-URL: https://gitlab.com/mediamoose/versions-client/repository/v0.2/archive.tar.gz
Keywords: versions-client,prometheus,versions,monitoring
Platform: UNKNOWN
Classifier: Development Status :: 3 - Alpha
Classifier: Framework :: Django
Classifier: Framework :: Django :: 1.8
Classifier: Framework :: Django :: 1.9
Classifier: Framework :: Django :: 1.10
Classifier: Framework :: Django :: 1.11
Classifier: Intended Audience :: Developers
Classifier: License :: OSI Approved :: MIT License
Classifier: Natural Language :: English
Classifier: Operating System :: POSIX :: Linux
Classifier: Programming Language :: Python
Classifier: Programming Language :: Python :: 2.7
Classifier: Programming Language :: Python :: 3.5
Classifier: Programming Language :: Python :: 3.6
Requires-Python: >=2.7
